casino_of_life/__init__.py
casino_of_life/agents/__init__.py
casino_of_life/agents/agent_orchestrator.py
casino_of_life/agents/caballo_loko.py
casino_of_life/agents/custom_agent.py
casino_of_life/agents/dynamic_agent.py
casino_of_life/chatTrainers/__init__.py
casino_of_life/chatTrainers/chat_trainer.py
casino_of_life/client_bridge/__init__.py
casino_of_life/client_bridge/action_mappers.py
casino_of_life/client_bridge/agent_factory.py
casino_of_life/client_bridge/chat_client.py
casino_of_life/client_bridge/parser.py
casino_of_life/client_bridge/retro_api.py
casino_of_life/client_bridge/reward_evaluators.py
casino_of_life/client_bridge/schema.py
casino_of_life/data/__init__.py
casino_of_life/data/contrib/__init__.py
casino_of_life/data/experimental/__init__.py
casino_of_life/data/stable/__init__.py
casino_of_life/game_environments/__init__.py
casino_of_life/game_environments/retro_env_loader.py
casino_of_life/utils/__init__.py
casino_of_life/utils/config.py
casino_of_life-0.2.6.dist-info/METADATA
casino_of_life-0.2.6.dist-info/WHEEL
casino_of_life-0.2.6.dist-info/entry_points.txt
casino_of_life-0.2.6.dist-info/top_level.txt
casino_of_life-0.2.6.dist-info/RECORD
