Metadata-Version: 2.2
Name: casino-of-life
Version: 0.2.6
Summary: A package for training AI agents to play retro games using natural language
Home-page: https://github.com/Cimai-Decentralized-Games/casino-of-life
Author: Cimai
Author-email: info@cimai.biz
Classifier: Development Status :: 3 - Alpha
Classifier: Intended Audience :: Developers
Classifier: Intended Audience :: Science/Research
Classifier: Programming Language :: Python :: 3
Classifier: Programming Language :: Python :: 3.8
Classifier: Programming Language :: Python :: 3.9
Classifier: Programming Language :: Python :: 3.10
Classifier: License :: OSI Approved :: MIT License
Classifier: Operating System :: OS Independent
Classifier: Topic :: Scientific/Engineering :: Artificial Intelligence
Requires-Python: >=3.8
Requires-Dist: fastapi>=0.68.0
Requires-Dist: uvicorn>=0.15.0
Requires-Dist: g4f>=0.1.0
Requires-Dist: websockets>=10.0
Requires-Dist: aiohttp>=3.8.0
Requires-Dist: pydantic>=1.8.0
Requires-Dist: python-dotenv>=0.19.0
Requires-Dist: gymnasium>=0.21.0
Requires-Dist: stable-retro>=0.9.3
Requires-Dist: stable-baselines3>=1.5.0
Requires-Dist: numpy>=1.19.0
Requires-Dist: torch>=1.9.0
Dynamic: author
Dynamic: author-email
Dynamic: classifier
Dynamic: description
Dynamic: description-content-type
Dynamic: home-page
Dynamic: requires-dist
Dynamic: requires-python
Dynamic: summary
